README.md
setup.cfg
setup.py
peto/__init__.py
peto.egg-info/PKG-INFO
peto.egg-info/SOURCES.txt
peto.egg-info/dependency_links.txt
peto.egg-info/not-zip-safe
peto.egg-info/requires.txt
peto.egg-info/top_level.txt
peto/application/__init__.py
peto/application/households.py
peto/application/people.py
peto/application/quanrantines.py
peto/application/samples.py
peto/application/system.py
peto/domainmodel/__init__.py
peto/domainmodel/base.py
peto/domainmodel/batchofresults.py
peto/domainmodel/exceptions.py
peto/domainmodel/household.py
peto/domainmodel/person.py
peto/domainmodel/quarantine.py
peto/domainmodel/sample.py